parallel_map/__init__.py
parallel_map/parallel_map.py
parallel_map/version.py
parallel_map/tests/__init__.py
parallel_map/tests/test_basic.py
parallel_map-0.2.1.dist-info/LICENSE.txt
parallel_map-0.2.1.dist-info/METADATA
parallel_map-0.2.1.dist-info/WHEEL
parallel_map-0.2.1.dist-info/top_level.txt
parallel_map-0.2.1.dist-info/RECORD
