Metadata-Version: 2.1
Name: parallel-map
Version: 0.2.1
Summary: Simple utility for parallel mapping.
Home-page: https://github.com/probcomp/parallel_map
Maintainer: Feras Saad
Maintainer-email: fsaad@mit.edu
License: Apache-2.0
Platform: UNKNOWN
Classifier: Development Status :: 2 - Pre-Alpha
Classifier: Intended Audience :: Science/Research
Classifier: License :: OSI Approved :: Apache Software License
Classifier: Programming Language :: Python :: 2.7
